mkdocs_moonstone/__init__.py
mkdocs_moonstone/base.html
mkdocs_moonstone/fonts.js
mkdocs_moonstone/footer.html
mkdocs_moonstone/main-nav.html
mkdocs_moonstone/main.html
mkdocs_moonstone/mkdocs_theme.yml
mkdocs_moonstone/nav-sub.html
mkdocs_moonstone/search-modal.html
mkdocs_moonstone/side-nav.html
mkdocs_moonstone/css/admonition.css
mkdocs_moonstone/css/base.css
mkdocs_moonstone/css/code-styles.css
mkdocs_moonstone/css/code-tabs.css
mkdocs_moonstone/css/font-awesome.min.css
mkdocs_moonstone/fonts/fontawesome-webfont.eot
mkdocs_moonstone/fonts/fontawesome-webfont.svg
mkdocs_moonstone/fonts/fontawesome-webfont.ttf
mkdocs_moonstone/fonts/fontawesome-webfont.woff
mkdocs_moonstone/fonts/fontawesome-webfont.woff2
mkdocs_moonstone/js/base.js
mkdocs_moonstone-0.2.0.dist-info/METADATA
mkdocs_moonstone-0.2.0.dist-info/WHEEL
mkdocs_moonstone-0.2.0.dist-info/entry_points.txt
mkdocs_moonstone-0.2.0.dist-info/top_level.txt
mkdocs_moonstone-0.2.0.dist-info/RECORD
