Metadata-Version: 2.1
Name: mkdocs-moonstone
Version: 0.2.0
Summary: Moonstone theme for MkDocs
Home-page: https://github.com/byrnereese/mkdocs-moonstone/
Author: Byrne Reese
Author-email: byrne@majordojo.com
License: UNKNOWN
Platform: UNKNOWN
Requires-Python: >=2.7.9,!=3.0.*,!=3.1.*,!=3.2.*,!=3.3.*
Requires-Dist: mkdocs (>=1.0)
Requires-Dist: mkdocs-git-committers-plugin (>=0.2.1)
Requires-Dist: mkdocs-bootstrap4 (>=0.1.5)
Requires-Dist: mkdocs-bootstrap-tables-plugin (>=0.1.1)
Requires-Dist: mkdocs-material (>=3.0)
